pyencoder/__init__.py
pyencoder/encoder.py
pyencoder-0.0.4.dist-info/LICENSE
pyencoder-0.0.4.dist-info/METADATA
pyencoder-0.0.4.dist-info/WHEEL
pyencoder-0.0.4.dist-info/top_level.txt
pyencoder-0.0.4.dist-info/RECORD
