Metadata-Version: 2.1
Name: pyencoder
Version: 0.0.4
Summary: encode and decode python list to string array
Home-page: https://github.com/simonkojima/pyencoder
Author: Simon Kojima
Author-email: simon.kojima@outlook.com
Project-URL: Bug Tracker, https://github.com/simonkojima/pyencoder/issues
Classifier: Programming Language :: Python :: 3
Classifier: License :: OSI Approved :: MIT License
Classifier: Operating System :: OS Independent
Requires-Python: >=3.6
License-File: LICENSE
